Metadata-Version: 2.1
Name: learnvcs
Version: 0.3.3
Summary: UNKNOWN
Home-page: https://github.com/LQR471814/learn.vcs-scraper
Author: LQR471814
Author-email: bramblefern1013@gmail.com
License: GPL-3.0
Keywords: vcs scraper
Platform: UNKNOWN
License-File: LICENSE
